{
  "_class": "symbolMaster",
  "allowsOverrides": true,
  "backgroundColor": {
    "_class": "color",
    "alpha": 1,
    "blue": 1,
    "green": 1,
    "red": 1
  },
  "booleanOperation": -1,
  "changeIdentifier": 279,
  "clippingMaskMode": 0,
  "do_objectID": "67DBB76E-06B8-4904-8473-5881C93F630B",
  "exportOptions": {
    "_class": "exportOptions",
    "exportFormats": [
    ],
    "includedLayerIds": [
    ],
    "layerOptions": 0,
    "shouldTrim": false
  },
  "frame": {
    "_class": "rect",
    "constrainProportions": false,
    "height": 342,
    "width": 661,
    "x": 13229,
    "y": 334
  },
  "groupLayout": {
    "_class": "MSImmutableInferredGroupLayout",
    "axis": 0,
    "layoutAnchor": 0
  },
  "hasBackgroundColor": false,
  "hasClickThrough": true,
  "hasClippingMask": false,
  "horizontalRulerData": {
    "_class": "rulerData",
    "base": 0,
    "guides": [
    ]
  },
  "includeBackgroundColorInExport": true,
  "includeBackgroundColorInInstance": true,
  "includeInCloudUpload": true,
  "isFixedToViewport": false,
  "isFlippedHorizontal": false,
  "isFlippedVertical": false,
  "isFlowHome": false,
  "isLocked": false,
  "isVisible": true,
  "layerListExpandedType": 0,
  "layers": [
    {
      "class": "symbolInstance",
      "id": "AFEC4FEF-FC0F-479B-9F5E-668FFFBA001D"
    },
    {
      "class": "symbolInstance",
      "id": "0033C414-2E07-4831-A378-FDC15112D5CA"
    },
    {
      "class": "symbolInstance",
      "id": "2862C84A-58F7-4CF2-850F-A879E9AE7B5E"
    },
    {
      "class": "symbolInstance",
      "id": "748314A7-0F20-4E0C-95FA-B77C13365127"
    },
    {
      "class": "symbolInstance",
      "id": "4B7305B1-CF9F-4E91-8EE9-E77BBA5DD840"
    }
  ],
  "maintainScrollPosition": false,
  "name": "accordion / default / group / open",
  "nameIsFixed": true,
  "overrideProperties": [
    {
      "_class": "MSImmutableOverrideProperty",
      "canOverride": true,
      "overrideName": "AFEC4FEF-FC0F-479B-9F5E-668FFFBA001D_symbolID"
    },
    {
      "_class": "MSImmutableOverrideProperty",
      "canOverride": true,
      "overrideName": "2862C84A-58F7-4CF2-850F-A879E9AE7B5E_symbolID"
    },
    {
      "_class": "MSImmutableOverrideProperty",
      "canOverride": true,
      "overrideName": "748314A7-0F20-4E0C-95FA-B77C13365127_symbolID"
    },
    {
      "_class": "MSImmutableOverrideProperty",
      "canOverride": true,
      "overrideName": "4B7305B1-CF9F-4E91-8EE9-E77BBA5DD840_symbolID"
    },
    {
      "_class": "MSImmutableOverrideProperty",
      "canOverride": true,
      "overrideName": "0033C414-2E07-4831-A378-FDC15112D5CA_symbolID"
    }
  ],
  "presetDictionary": {
  },
  "resizesContent": false,
  "resizingConstraint": 63,
  "resizingType": 0,
  "rotation": 0,
  "shouldBreakMaskChain": true,
  "style": {
    "_class": "style",
    "blur": {
      "_class": "blur",
      "center": "{0.5, 0.5}",
      "isEnabled": false,
      "motionAngle": 0,
      "radius": 10,
      "saturation": 1,
      "type": 0
    },
    "borderOptions": {
      "_class": "borderOptions",
      "dashPattern": [
      ],
      "isEnabled": true,
      "lineCapStyle": 0,
      "lineJoinStyle": 0
    },
    "borders": [
    ],
    "colorControls": {
      "_class": "colorControls",
      "brightness": 0,
      "contrast": 1,
      "hue": 0,
      "isEnabled": false,
      "saturation": 1
    },
    "contextSettings": {
      "_class": "graphicsContextSettings",
      "blendMode": 0,
      "opacity": 1
    },
    "do_objectID": "C5CAC638-5FB6-4065-A068-9C52CF346E80",
    "endMarkerType": 0,
    "fills": [
    ],
    "innerShadows": [
    ],
    "miterLimit": 10,
    "shadows": [
    ],
    "startMarkerType": 0,
    "windingRule": 1
  },
  "symbolID": "7B4F64D7-0D51-4E60-BF7E-FEDC0A27EB5D",
  "verticalRulerData": {
    "_class": "rulerData",
    "base": 0,
    "guides": [
    ]
  }
}